sdsheets/__init__.py
sdsheets/conftest.py
sdsheets/examples/__init__.py
sdsheets/examples/example1.py
sdsheets-1.0.3.dist-info/LICENSE
sdsheets-1.0.3.dist-info/METADATA
sdsheets-1.0.3.dist-info/WHEEL
sdsheets-1.0.3.dist-info/top_level.txt
sdsheets-1.0.3.dist-info/RECORD
