Metadata-Version: 2.1
Name: sdsheets
Version: 1.0.3
Summary: Lib para recuperar informações de planilhas do Google Spreadsheets
Home-page: https://bitbucket.org/santodigital/sdsheets
Author: Rodrigo Gonçalves
Author-email: rodrigo@santodigital.com.br
License: UNKNOWN
Platform: UNKNOWN
Classifier: Programming Language :: Python :: 3
Classifier: License :: OSI Approved :: MIT License
Classifier: Operating System :: OS Independent
Requires-Python: >=3.6
